cortex_xdr_client/__init__.py
cortex_xdr_client/api/__init__.py
cortex_xdr_client/api/actions_api.py
cortex_xdr_client/api/alerts_api.py
cortex_xdr_client/api/authentication.py
cortex_xdr_client/api/base_api.py
cortex_xdr_client/api/download_api.py
cortex_xdr_client/api/endpoints_api.py
cortex_xdr_client/api/incidents_api.py
cortex_xdr_client/api/ioc_api.py
cortex_xdr_client/api/models/__init__.py
cortex_xdr_client/api/models/action_status.py
cortex_xdr_client/api/models/alerts.py
cortex_xdr_client/api/models/endpoints.py
cortex_xdr_client/api/models/exceptions.py
cortex_xdr_client/api/models/filters.py
cortex_xdr_client/api/models/incidents.py
cortex_xdr_client/api/models/ioc.py
cortex_xdr_client/api/models/scripts.py
cortex_xdr_client/api/scripts_api.py
cortex_xdr_client/api/xql_api.py
cortex_xdr_client/client.py
cortex_xdr_client-1.8.9.dist-info/LICENSE
cortex_xdr_client-1.8.9.dist-info/METADATA
cortex_xdr_client-1.8.9.dist-info/WHEEL
cortex_xdr_client-1.8.9.dist-info/RECORD
