Metadata-Version: 2.1
Name: cortex-xdr-client
Version: 1.8.9
Summary: API client for Cortex XDR Prevent
Home-page: https://github.com/ebarti/cortex-xdr-client
License: MIT
Author: ebarti
Requires-Python: >=3.8,<4.0
Classifier: License :: OSI Approved :: MIT License
Classifier: Programming Language :: Python :: 3
Classifier: Programming Language :: Python :: 3.8
Classifier: Programming Language :: Python :: 3.9
Classifier: Programming Language :: Python :: 3.10
Classifier: Programming Language :: Python :: 3.11
Classifier: Programming Language :: Python :: 3.12
Requires-Dist: pydantic (>=1.8.2,<2.0.0)
Requires-Dist: requests (>=2.26.0,<3.0.0)
Project-URL: Repository, https://github.com/ebarti/cortex-xdr-client
